README
README.md
setup.cfg
setup.py
src/azdsdr/__init__.py
src/azdsdr/readers.py
src/azdsdr/tools.py
src/azdsdr.egg-info/PKG-INFO
src/azdsdr.egg-info/SOURCES.txt
src/azdsdr.egg-info/dependency_links.txt
src/azdsdr.egg-info/requires.txt
src/azdsdr.egg-info/top_level.txt