Metadata-Version: 2.1
Name: azdsdr
Version: 1.230123.1
Summary: This package provide functions and tools for accessing data in a easy way.
Home-page: https://github.com/xhinker/azdsdr
Author: Andrew Zhu
Author-email: xhinker@hotmail.com
License: Apache License
Keywords: DS Data Reader
